mosquito/__init__.py
mosquito/api.py
mosquito/scheduler.py
mosquito/session.py
mosquito/swarm.py
mosquito/utils.py
mosquito/tests/__init__.py
mosquito/tests/__main__.py
mosquito/tests/test_api.py
mosquito/tests/test_scheduler.py
mosquito/tests/test_session.py
mosquito/tests/test_swarm.py
mosquito/tests/test_utils.py
mosquito/tests/utils.py
mosquito-0.3.2.dist-info/LICENSE
mosquito-0.3.2.dist-info/METADATA
mosquito-0.3.2.dist-info/WHEEL
mosquito-0.3.2.dist-info/top_level.txt
mosquito-0.3.2.dist-info/RECORD
