Metadata-Version: 2.1
Name: mosquito
Version: 0.3.2
Summary: a request obfuscator and web scraping toolkit
Home-page: https://gitlab.com/luoc0815/mosquito
Author: luoc
Author-email: luoc@posteo.org
License: UNKNOWN
Platform: UNKNOWN
Classifier: Programming Language :: Python :: 3
Classifier: Programming Language :: Python :: 3.6
Classifier: License :: OSI Approved :: Apache Software License
Classifier: Operating System :: OS Independent
Provides-Extra: develop
